langfuse/__init__.py
langfuse/_client/attributes.py
langfuse/_client/client.py
langfuse/_client/constants.py
langfuse/_client/datasets.py
langfuse/_client/environment_variables.py
langfuse/_client/get_client.py
langfuse/_client/observe.py
langfuse/_client/propagation.py
langfuse/_client/resource_manager.py
langfuse/_client/span.py
langfuse/_client/span_processor.py
langfuse/_client/utils.py
langfuse/_task_manager/media_manager.py
langfuse/_task_manager/media_upload_consumer.py
langfuse/_task_manager/media_upload_queue.py
langfuse/_task_manager/score_ingestion_consumer.py
langfuse/_utils/__init__.py
langfuse/_utils/environment.py
langfuse/_utils/error_logging.py
langfuse/_utils/parse_error.py
langfuse/_utils/prompt_cache.py
langfuse/_utils/request.py
langfuse/_utils/serializer.py
langfuse/api/README.md
langfuse/api/__init__.py
langfuse/api/client.py
langfuse/api/core/__init__.py
langfuse/api/core/api_error.py
langfuse/api/core/client_wrapper.py
langfuse/api/core/datetime_utils.py
langfuse/api/core/file.py
langfuse/api/core/http_client.py
langfuse/api/core/jsonable_encoder.py
langfuse/api/core/pydantic_utilities.py
langfuse/api/core/query_encoder.py
langfuse/api/core/remove_none_from_dict.py
langfuse/api/core/request_options.py
langfuse/api/reference.md
langfuse/api/resources/__init__.py
langfuse/api/resources/annotation_queues/__init__.py
langfuse/api/resources/annotation_queues/client.py
langfuse/api/resources/annotation_queues/types/__init__.py
langfuse/api/resources/annotation_queues/types/annotation_queue.py
langfuse/api/resources/annotation_queues/types/annotation_queue_assignment_request.py
langfuse/api/resources/annotation_queues/types/annotation_queue_item.py
langfuse/api/resources/annotation_queues/types/annotation_queue_object_type.py
langfuse/api/resources/annotation_queues/types/annotation_queue_status.py
langfuse/api/resources/annotation_queues/types/create_annotation_queue_assignment_response.py
pixie_sdk-0.2.9.dist-info/METADATA
pixie_sdk-0.2.9.dist-info/WHEEL
pixie_sdk-0.2.9.dist-info/entry_points.txt
pixie_sdk-0.2.9.dist-info/licenses/LICENSE
pixie_sdk-0.2.9.dist-info/RECORD
