Metadata-Version: 2.4
Name: pixie-sdk
Version: 0.2.9
Summary: Interactive debugging tool for AI applications
License: MIT
License-File: LICENSE
Author: Yiou Li
Author-email: yol@gopixie.ai
Requires-Python: >=3.10,<4.0
Classifier: License :: OSI Approved :: MIT License
Classifier: Programming Language :: Python :: 3
Classifier: Programming Language :: Python :: 3.10
Classifier: Programming Language :: Python :: 3.11
Classifier: Programming Language :: Python :: 3.12
Classifier: Programming Language :: Python :: 3.13
Classifier: Programming Language :: Python :: 3.14
Requires-Dist: backoff (>=1.10.0)
Requires-Dist: colorlog (>=6.10.1)
Requires-Dist: docstring-parser (>=0.17.0,<0.18.0)
Requires-Dist: dotenv (>=0.9.9)
Requires-Dist: fastapi (>=0.128.0)
Requires-Dist: httpx (>=0.15.4,<1.0)
Requires-Dist: janus (>=2.0.0)
Requires-Dist: opentelemetry-api (>=1.33.1,<2.0.0)
Requires-Dist: opentelemetry-exporter-otlp-proto-http (>=1.33.1,<2.0.0)
Requires-Dist: opentelemetry-sdk (>=1.33.1,<2.0.0)
Requires-Dist: packaging (>=23.2,<26.0)
Requires-Dist: pixie-prompts[server] (>=0.1.9,<0.2.0)
Requires-Dist: pydantic (>=1.10.7,<3.0)
Requires-Dist: requests (>=2,<3)
Requires-Dist: strawberry-graphql (>=0.288.1)
Requires-Dist: uvicorn (>=0.40.0)
Requires-Dist: websockets (>=15.0.1)
Requires-Dist: wrapt (>=1.14,<2.0)
Project-URL: Changelog, https://github.com/yiouli/pixie-sdk-py/commits/main/
Project-URL: Documentation, https://yiouli.github.io/pixie-sdk-py/
Project-URL: Homepage, https://gopixie.ai
Project-URL: Issues, https://github.com/yiouli/pixie-sdk-py/issues
Project-URL: Repository, https://github.com/yiouli/pixie-sdk-py
